flask_desktop_ui/__init__.py
flask_desktop_ui/chromium_browser_wrapper.py
flask_desktop_ui-0.3.dist-info/LICENSE
flask_desktop_ui-0.3.dist-info/METADATA
flask_desktop_ui-0.3.dist-info/WHEEL
flask_desktop_ui-0.3.dist-info/top_level.txt
flask_desktop_ui-0.3.dist-info/RECORD
